xbi/__init__.py
xbi-0.0.0.dist-info/METADATA
xbi-0.0.0.dist-info/WHEEL
xbi-0.0.0.dist-info/top_level.txt
xbi-0.0.0.dist-info/RECORD
