Metadata-Version: 2.1
Name: xbi
Version: 0.0.0
Summary: Simulation-based Inference with JAX
Home-page: https://github.com/francois-rozet/xbi
Author: François Rozet
Author-email: francois.rozet@outlook.com
License: UNKNOWN
Keywords: parameter inference simulator jax
Platform: UNKNOWN
Classifier: Programming Language :: Python :: 3
Classifier: License :: OSI Approved :: MIT License
Classifier: Operating System :: OS Independent
Requires-Python: >=3.9
Requires-Dist: jax (>=0.2.24)
